data_analysis_mcp/__init__.py
data_analysis_mcp/app.py
data_analysis_mcp/config/__init__.py
data_analysis_mcp/config/config.py
data_analysis_mcp/services/__init__.py
data_analysis_mcp/services/data_analysis.py
data_analysis_mcp/utils/__init__.py
data_analysis_mcp/utils/logger.py
data_analysis_mcp-0.1.8.dist-info/METADATA
data_analysis_mcp-0.1.8.dist-info/WHEEL
data_analysis_mcp-0.1.8.dist-info/entry_points.txt
data_analysis_mcp-0.1.8.dist-info/RECORD
