Metadata-Version: 2.4
Name: data_analysis_mcp
Version: 0.1.8
Summary: 数据分析MCP服务
Author-email: Data Analysis Team <example@example.com>
Classifier: License :: OSI Approved :: MIT License
Classifier: Operating System :: OS Independent
Classifier: Programming Language :: Python :: 3
Requires-Python: >=3.8
Requires-Dist: aiohttp>=3.8.1
Requires-Dist: mcp>=0.1.0
Requires-Dist: python-dotenv>=0.20.0
Requires-Dist: requests>=2.27.1
Provides-Extra: dev
Requires-Dist: black>=22.1.0; extra == 'dev'
Requires-Dist: flake8>=4.0.1; extra == 'dev'
Requires-Dist: isort>=5.10.1; extra == 'dev'
Requires-Dist: pytest>=7.0.0; extra == 'dev'
